Workbook

Sheet Respostas ao formulário 1
A1: Carimbo de data/hora | B1: Pergunta sem título

Sheet mercado_acoes
A1: Código Cliente | B1: Nome Cliente | C1: Email Cliente | D1: Operação | E1: Ticker | F1: Preco | G1: Data | H1: Dia | I1: Mês | J1: Ano | K1: Normalizar
A2: 30 | B2: Larissa Gomes | C2: larissa.gomes94@exemplo.com | D2: Compra | E2: IGTA3 | F2: 10.3 | G2: 44927 | H2: =G2 -> 44927 | I2: =G2 -> 44927 | J2: =G2 -> 44927 | K2: =(F2-MIN(F:F))/(MAX(F:F)-MIN(F:F)) -> 0.1139529
A3: 78 | B3: Gabriela Mendes | C3: gabriela.mendes90@exemplo.com | D3: Venda | E3: VIVT3 | F3: 53.3 | G3: 44927 | H3: =G3 -> 44927 | I3: =G3 -> 44927 | J3: =G3 -> 44927 | K3: =(F3-MIN(F:F))/(MAX(F:F)-MIN(F:F)) -> 0.65839453
A4: 50 | B4: Camila Rocha | C4: camila.rocha10@exemplo.com | D4: Compra | E4: LREN3 | F4: 21.69 | G4: 44927 | H4: =G4 -> 44927 | I4: =G4 -> 44927 | J4: =G4 -> 44927 | K4: =(F4-MIN(F:F))/(MAX(F:F)-MIN(F:F)) -> 0.25816662
A5: 80 | B5: Beatriz Almeida | C5: beatriz.almeida66@exemplo.com | D5: Venda | E5: PETR4 | F5: 39.74 | G5: 44928 | H5: =G5 -> 44928 | I5: =G5 -> 44928 | J5: =G5 -> 44928 | K5: =(F5-MIN(F:F))/(MAX(F:F)-MIN(F:F)) -> 0.4867055
A6: 68 | B6: Sofia Melo | C6: sofia.melo31@exemplo.com | D6: Compra | E6: CSAN3 | F6: 17.96 | G6: 44928 | H6: =G6 -> 44928 | I6: =G6 -> 44928 | J6: =G6 -> 44928 | K6: =(F6-MIN(F:F))/(MAX(F:F)-MIN(F:F)) -> 0.21093948
A7: 48 | B7: Sofia Melo | C7: sofia.melo78@exemplo.com | D7: Venda | E7: ABEV3 | F7: 11.95 | G7: 44928 | H7: =G7 -> 44928 | I7: =G7 -> 44928 | J7: =G7 -> 44928 | K7: =(F7-MIN(F:F))/(MAX(F:F)-MIN(F:F)) -> 0.13484426
A8: 100 | B8: Lucas Cardoso | C8: lucas.cardoso77@exemplo.com | D8: Compra | E8: ITUB4 | F8: 24.53 | G8: 44928 | H8: =G8 -> 44928 | I8: =G8 -> 44928 | J8: =G8 -> 44928 | K8: =(F8-MIN(F:F))/(MAX(F:F)-MIN(F:F)) -> 0.2941251
A9: 30 | B9: Larissa Gomes | C9: larissa.gomes94@exemplo.com | D9: Compra | E9: RENT3 | F9: 46.74 | G9: 44928 | H9: =G9 -> 44928 | I9: =G9 -> 44928 | J9: =G9 -> 44928 | K9: =(F9-MIN(F:F))/(MAX(F:F)-MIN(F:F)) -> 0.57533553
A10: 81 | B10: Clara Costa | C10: clara.costa91@exemplo.com | D10: Venda | E10: VALE3 | F10: 65.39 | G10: 44928 | H10: =G10 -> 44928 | I10: =G10 -> 44928 | J10: =G10 -> 44928 | K10: =(F10-MIN(F:F))/(MAX(F:F)-MIN(F:F)) -> 0.81147126
A11: 15 | B11: Felipe Ribeiro | C11: felipe.ribeiro44@exemplo.com | D11: Venda | E11: BBAS3 | F11: 56.68 | G11: 44929 | H11: =G11 -> 44929 | I11: =G11 -> 44929 | J11: =G11 -> 44929 | K11: =(F11-MIN(F:F))/(MAX(F:F)-MIN(F:F)) -> 0.70119017
A12: 86 | B12: Guilherme Oliveira | C12: guilherme.oliveira36@exemplo.com | D12: Venda | E12: PETR4 | F12: 26.99 | G12: 44929 | H12: =G12 -> 44929 | I12: =G12 -> 44929 | J12: =G12 -> 44929 | K12: =(F12-MIN(F:F))/(MAX(F:F)-MIN(F:F)) -> 0.32527222
A13: 60 | B13: Marcos Costa | C13: marcos.costa57@exemplo.com | D13: Venda | E13: VALE3 | F13: 78.94 | G13: 44929 | H13: =G13 -> 44929 | I13: =G13 -> 44929 | J13: =G13 -> 44929 | K13: =(F13-MIN(F:F))/(MAX(F:F)-MIN(F:F)) -> 0.98303368
... A2001: 33 | B2001: Gustavo Souza | C2001: gustavo.souza88@exemplo.com | D2001: Compra | E2001: LREN3 | F2001: 20.52 | G2001: 45288 | H2001: =G2001 -> 45288 | I2001: =G2001 -> 45288 | J2001: =G2001 -> 45288 | K2001: =(F2001-MIN(F:F))/(MAX(F:F)-MIN(F:F)) -> 0.24335275

Sheet cliente_lucro_prejuizo

Sheet cliente_compra_venda

Sheet compra_venda

Sheet mercado_acoes_compra
A1: Código Cliente | B1: Nome Cliente | C1: Email Cliente | D1: Operação | E1: Ticker | F1: Preco | G1: Data | H1: Dia | I1: Mês | J1: Ano | K1: Normalizar
A2: 30 | B2: Larissa Gomes | C2: larissa.gomes94@exemplo.com | D2: Compra | E2: IGTA3 | F2: 10.3 | G2: 44927 | H2: =G2 -> 44927 | I2: =G2 -> 44927 | J2: =G2 -> 44927 | K2: =(F2-MIN(F:F))/(MAX(F:F)-MIN(F:F)) -> 0.1139529
A3: 78 | B3: Gabriela Mendes | C3: gabriela.mendes90@exemplo.com | D3: Venda | E3: VIVT3 | F3: 53.3 | G3: 44927 | H3: =G3 -> 44927 | I3: =G3 -> 44927 | J3: =G3 -> 44927 | K3: =(F3-MIN(F:F))/(MAX(F:F)-MIN(F:F)) -> 0.65839453
A4: 50 | B4: Camila Rocha | C4: camila.rocha10@exemplo.com | D4: Compra | E4: LREN3 | F4: 21.69 | G4: 44927 | H4: =G4 -> 44927 | I4: =G4 -> 44927 | J4: =G4 -> 44927 | K4: =(F4-MIN(F:F))/(MAX(F:F)-MIN(F:F)) -> 0.25816662
A5: 80 | B5: Beatriz Almeida | C5: beatriz.almeida66@exemplo.com | D5: Venda | E5: PETR4 | F5: 39.74 | G5: 44928 | H5: =G5 -> 44928 | I5: =G5 -> 44928 | J5: =G5 -> 44928 | K5: =(F5-MIN(F:F))/(MAX(F:F)-MIN(F:F)) -> 0.4867055
A6: 68 | B6: Sofia Melo | C6: sofia.melo31@exemplo.com | D6: Compra | E6: CSAN3 | F6: 17.96 | G6: 44928 | H6: =G6 -> 44928 | I6: =G6 -> 44928 | J6: =G6 -> 44928 | K6: =(F6-MIN(F:F))/(MAX(F:F)-MIN(F:F)) -> 0.21093948
A7: 48 | B7: Sofia Melo | C7: sofia.melo78@exemplo.com | D7: Venda | E7: ABEV3 | F7: 11.95 | G7: 44928 | H7: =G7 -> 44928 | I7: =G7 -> 44928 | J7: =G7 -> 44928 | K7: =(F7-MIN(F:F))/(MAX(F:F)-MIN(F:F)) -> 0.13484426
A8: 100 | B8: Lucas Cardoso | C8: lucas.cardoso77@exemplo.com | D8: Compra | E8: ITUB4 | F8: 24.53 | G8: 44928 | H8: =G8 -> 44928 | I8: =G8 -> 44928 | J8: =G8 -> 44928 | K8: =(F8-MIN(F:F))/(MAX(F:F)-MIN(F:F)) -> 0.2941251
A9: 30 | B9: Larissa Gomes | C9: larissa.gomes94@exemplo.com | D9: Compra | E9: RENT3 | F9: 46.74 | G9: 44928 | H9: =G9 -> 44928 | I9: =G9 -> 44928 | J9: =G9 -> 44928 | K9: =(F9-MIN(F:F))/(MAX(F:F)-MIN(F:F)) -> 0.57533553
A10: 81 | B10: Clara Costa | C10: clara.costa91@exemplo.com | D10: Venda | E10: VALE3 | F10: 65.39 | G10: 44928 | H10: =G10 -> 44928 | I10: =G10 -> 44928 | J10: =G10 -> 44928 | K10: =(F10-MIN(F:F))/(MAX(F:F)-MIN(F:F)) -> 0.81147126
A11: 15 | B11: Felipe Ribeiro | C11: felipe.ribeiro44@exemplo.com | D11: Venda | E11: BBAS3 | F11: 56.68 | G11: 44929 | H11: =G11 -> 44929 | I11: =G11 -> 44929 | J11: =G11 -> 44929 | K11: =(F11-MIN(F:F))/(MAX(F:F)-MIN(F:F)) -> 0.70119017
A12: 86 | B12: Guilherme Oliveira | C12: guilherme.oliveira36@exemplo.com | D12: Venda | E12: PETR4 | F12: 26.99 | G12: 44929 | H12: =G12 -> 44929 | I12: =G12 -> 44929 | J12: =G12 -> 44929 | K12: =(F12-MIN(F:F))/(MAX(F:F)-MIN(F:F)) -> 0.32527222
A13: 60 | B13: Marcos Costa | C13: marcos.costa57@exemplo.com | D13: Venda | E13: VALE3 | F13: 78.94 | G13: 44929 | H13: =G13 -> 44929 | I13: =G13 -> 44929 | J13: =G13 -> 44929 | K13: =(F13-MIN(F:F))/(MAX(F:F)-MIN(F:F)) -> 0.98303368
... A2001: 33 | B2001: Gustavo Souza | C2001: gustavo.souza88@exemplo.com | D2001: Compra | E2001: LREN3 | F2001: 20.52 | G2001: 45288 | H2001: =G2001 -> 45288 | I2001: =G2001 -> 45288 | J2001: =G2001 -> 45288 | K2001: =(F2001-MIN(F:F))/(MAX(F:F)-MIN(F:F)) -> 0.24335275

Sheet mercado_acoes_venda
A1: Código Cliente | B1: Nome Cliente | C1: Email Cliente | D1: Operação | E1: Ticker | F1: Preco | G1: Data | H1: Dia | I1: Mês | J1: Ano | K1: Normalizar
A2: 30 | B2: Larissa Gomes | C2: larissa.gomes94@exemplo.com | D2: Compra | E2: IGTA3 | F2: 10.3 | G2: 44927 | H2: =G2 -> 44927 | I2: =G2 -> 44927 | J2: =G2 -> 44927 | K2: =(F2-MIN(F:F))/(MAX(F:F)-MIN(F:F)) -> 0.1139529
A3: 78 | B3: Gabriela Mendes | C3: gabriela.mendes90@exemplo.com | D3: Venda | E3: VIVT3 | F3: 53.3 | G3: 44927 | H3: =G3 -> 44927 | I3: =G3 -> 44927 | J3: =G3 -> 44927 | K3: =(F3-MIN(F:F))/(MAX(F:F)-MIN(F:F)) -> 0.65839453
A4: 50 | B4: Camila Rocha | C4: camila.rocha10@exemplo.com | D4: Compra | E4: LREN3 | F4: 21.69 | G4: 44927 | H4: =G4 -> 44927 | I4: =G4 -> 44927 | J4: =G4 -> 44927 | K4: =(F4-MIN(F:F))/(MAX(F:F)-MIN(F:F)) -> 0.25816662
A5: 80 | B5: Beatriz Almeida | C5: beatriz.almeida66@exemplo.com | D5: Venda | E5: PETR4 | F5: 39.74 | G5: 44928 | H5: =G5 -> 44928 | I5: =G5 -> 44928 | J5: =G5 -> 44928 | K5: =(F5-MIN(F:F))/(MAX(F:F)-MIN(F:F)) -> 0.4867055
A6: 68 | B6: Sofia Melo | C6: sofia.melo31@exemplo.com | D6: Compra | E6: CSAN3 | F6: 17.96 | G6: 44928 | H6: =G6 -> 44928 | I6: =G6 -> 44928 | J6: =G6 -> 44928 | K6: =(F6-MIN(F:F))/(MAX(F:F)-MIN(F:F)) -> 0.21093948
A7: 48 | B7: Sofia Melo | C7: sofia.melo78@exemplo.com | D7: Venda | E7: ABEV3 | F7: 11.95 | G7: 44928 | H7: =G7 -> 44928 | I7: =G7 -> 44928 | J7: =G7 -> 44928 | K7: =(F7-MIN(F:F))/(MAX(F:F)-MIN(F:F)) -> 0.13484426
A8: 100 | B8: Lucas Cardoso | C8: lucas.cardoso77@exemplo.com | D8: Compra | E8: ITUB4 | F8: 24.53 | G8: 44928 | H8: =G8 -> 44928 | I8: =G8 -> 44928 | J8: =G8 -> 44928 | K8: =(F8-MIN(F:F))/(MAX(F:F)-MIN(F:F)) -> 0.2941251
A9: 30 | B9: Larissa Gomes | C9: larissa.gomes94@exemplo.com | D9: Compra | E9: RENT3 | F9: 46.74 | G9: 44928 | H9: =G9 -> 44928 | I9: =G9 -> 44928 | J9: =G9 -> 44928 | K9: =(F9-MIN(F:F))/(MAX(F:F)-MIN(F:F)) -> 0.57533553
A10: 81 | B10: Clara Costa | C10: clara.costa91@exemplo.com | D10: Venda | E10: VALE3 | F10: 65.39 | G10: 44928 | H10: =G10 -> 44928 | I10: =G10 -> 44928 | J10: =G10 -> 44928 | K10: =(F10-MIN(F:F))/(MAX(F:F)-MIN(F:F)) -> 0.81147126
A11: 15 | B11: Felipe Ribeiro | C11: felipe.ribeiro44@exemplo.com | D11: Venda | E11: BBAS3 | F11: 56.68 | G11: 44929 | H11: =G11 -> 44929 | I11: =G11 -> 44929 | J11: =G11 -> 44929 | K11: =(F11-MIN(F:F))/(MAX(F:F)-MIN(F:F)) -> 0.70119017
A12: 86 | B12: Guilherme Oliveira | C12: guilherme.oliveira36@exemplo.com | D12: Venda | E12: PETR4 | F12: 26.99 | G12: 44929 | H12: =G12 -> 44929 | I12: =G12 -> 44929 | J12: =G12 -> 44929 | K12: =(F12-MIN(F:F))/(MAX(F:F)-MIN(F:F)) -> 0.32527222
A13: 60 | B13: Marcos Costa | C13: marcos.costa57@exemplo.com | D13: Venda | E13: VALE3 | F13: 78.94 | G13: 44929 | H13: =G13 -> 44929 | I13: =G13 -> 44929 | J13: =G13 -> 44929 | K13: =(F13-MIN(F:F))/(MAX(F:F)-MIN(F:F)) -> 0.98303368
... A2001: 33 | B2001: Gustavo Souza | C2001: gustavo.souza88@exemplo.com | D2001: Compra | E2001: LREN3 | F2001: 20.52 | G2001: 45288 | H2001: =G2001 -> 45288 | I2001: =G2001 -> 45288 | J2001: =G2001 -> 45288 | K2001: =(F2001-MIN(F:F))/(MAX(F:F)-MIN(F:F)) -> 0.24335275

Sheet Estatisticas
B1: Tabela de estatisticas (mercado de ações)
B2: Soma | C2: =SUM(mercado_acoes!F:F) -> 50905.24
B3: Mínimo | C3: =MIN(mercado_acoes!F:F) -> 1.3
B4: Máximo | C4: =MAX(mercado_acoes!F:F) -> 80.28
B5: Média | C5: =AVERAGE(mercado_acoes!F:F) -> 25.45262
B6: Mediana | C6: =MEDIAN(mercado_acoes!F:F) -> 19.245
B7: Moda | C7: =MODE(mercado_acoes!F:F) -> 10.71
B8: Desvio Padrão | C8: =STDEV(C2:C7) -> 20770.811
B9: Variância | C9: =STDEV(C3:C8) -> 8468.5081
B17: Codigo Cliente | C17: Nome | D17: Email
B18: 50 | C18: =VLOOKUP(B18,mercado_acoes!A:B,2,FALSE) -> Camila Rocha | D18: =VLOOKUP(C18,mercado_acoes!B:C,2,FALSE) -> camila.rocha10@exemplo.com
B19: 5 | C19: =VLOOKUP(B19,mercado_acoes!A:B,2,FALSE) -> Bruno Rodrigues | D19: =VLOOKUP(C19,mercado_acoes!B:C,2,FALSE) -> bruno.rodrigues89@exemplo.com
B20: 50 | C20: =VLOOKUP(B20,mercado_acoes!A:B,2,FALSE) -> Camila Rocha | D20: =VLOOKUP(C20,mercado_acoes!B:C,2,FALSE) -> camila.rocha10@exemplo.com

Sheet Cliente
B1: Email | C1: Número total de Transações | D1: Número total de vendas | E1: Media de Transações
B2: luis.lima28@exemplo.com | C2: =COUNTIF(mercado_acoes!C:C,B2) -> 20 | D2: =SUMIF(mercado_acoes!C:C,B2,mercado_acoes!F:F) -> 496.35 | E2: =AVERAGEIF(mercado_acoes!C:C,B2,mercado_acoes!F:F) -> 24.8175 | H2: Estilo de Cliente | I2: Condicional | J2: Valor de Transações | K2: Condicional
B3: gabriela.mendes90@exemplo.com | C3: =COUNTIF(mercado_acoes!C:C,B3) -> 20 | D3: =SUMIF(mercado_acoes!C:C,B3,mercado_acoes!F:F) -> 461.11 | E3: =AVERAGEIF(mercado_acoes!C:C,B3,mercado_acoes!F:F) -> 23.0555 | H3: “Perfil Agressivo” | I3: 20 ≥ operações | J3: Grandes Transações | K3: 20 ≥ operações
B4: clara.costa91@exemplo.com | C4: =COUNTIF(mercado_acoes!C:C,B4) -> 20 | D4: =SUMIF(mercado_acoes!C:C,B4,mercado_acoes!F:F) -> 469.72 | E4: =AVERAGEIF(mercado_acoes!C:C,B4,mercado_acoes!F:F) -> 23.486 | H4: “Perfil Moderado” | I4: 5 a 19 operações | J4: Pequenas Transações | K4: 20 < operações
H5: “Perfil Conservador” | I5: 0 a 4 operações
B6: Estilo de perfil | D6: Estilo de gastos
B7: =IF(C2>=20,H3,IF(C2>=5,H4,H5)) -> “Perfil Agressivo” | D7: =IF(E2>=20,J3,J4) -> Grandes Transações | H7: Codigo Cliente | I7: Nome | J7: Email
B8: =IF(C3>=20,H3,IF(C3>=5,H4,H5)) -> “Perfil Agressivo” | D8: =IF(E3>=20,J3,J4) -> Grandes Transações | H8: 50 | I8: =VLOOKUP(H8,mercado_acoes!A:B,2,FALSE) -> Camila Rocha | J8: =VLOOKUP(I8,mercado_acoes!B:C,2,FALSE) -> camila.rocha10@exemplo.com
B9: =IF(C4>=20,H3,IF(C4>=5,H4,H5)) -> “Perfil Agressivo” | D9: =IF(E4>=20,J3,J4) -> Grandes Transações | H9: 5 | I9: =VLOOKUP(H9,mercado_acoes!A:B,2,FALSE) -> Bruno Rodrigues | J9: =VLOOKUP(I9,mercado_acoes!B:C,2,FALSE) -> bruno.rodrigues89@exemplo.com
H10: 50 | I10: =VLOOKUP(H10,mercado_acoes!A:B,2,FALSE) -> Camila Rocha | J10: =VLOOKUP(I10,mercado_acoes!B:C,2,FALSE) -> camila.rocha10@exemplo.com

Sheet tendencia_temporal
A1: Mês | B1: Ano | C1: Quantidade de operacoes | E1: Previsão da Operação | G1: Curva de erro
A2: 1 | B2: 2023 | C2: =COUNTIFS(mercado_acoes!G:G,">=01/01/2023",mercado_acoes!G:G,"<=31/01/2023") -> 152 | E2: =FORECAST(12,C2:C12,A2:A12) -> 172.01818 | G2: =E2-C13 -> -14.981818
A3: 2 | B3: 2023 | C3: =COUNTIFS(mercado_acoes!G:G,">=01/02/2023",mercado_acoes!G:G,"<=28/02/2023") -> 172
A4: 3 | B4: 2023 | C4: =COUNTIFS(mercado_acoes!G:G,">=01/03/2023",mercado_acoes!G:G,"<=31/03/2023") -> 148
A5: 4 | B5: 2023 | C5: =COUNTIFS(mercado_acoes!G:G,">=01/04/2023",mercado_acoes!G:G,"<=30/04/2023") -> 169
A6: 5 | B6: 2023 | C6: =COUNTIFS(mercado_acoes!G:G,">=01/05/2023",mercado_acoes!G:G,"<=31/05/2023") -> 167
A7: 6 | B7: 2023 | C7: =COUNTIFS(mercado_acoes!G:G,">=01/06/2023",mercado_acoes!G:G,"<=30/06/2023") -> 172
A8: 7 | B8: 2023 | C8: =COUNTIFS(mercado_acoes!G:G,">=01/07/2023",mercado_acoes!G:G,"<=31/07/2023") -> 158
A9: 8 | B9: 2023 | C9: =COUNTIFS(mercado_acoes!G:G,">=01/08/2023",mercado_acoes!G:G,"<=31/08/2023") -> 180
A10: 9 | B10: 2023 | C10: =COUNTIFS(mercado_acoes!G:G,">=01/09/2023",mercado_acoes!G:G,"<=30/09/2023") -> 154
A11: 10 | B11: 2023 | C11: =COUNTIFS(mercado_acoes!G:G,">=01/10/2023",mercado_acoes!G:G,"<=31/10/2023") -> 156
A12: 11 | B12: 2023 | C12: =COUNTIFS(mercado_acoes!G:G,">=01/11/2023",mercado_acoes!G:G,"<=30/11/2023") -> 185
A13: 12 | B13: 2023 | C13: =COUNTIFS(mercado_acoes!G:G,">=01/12/2023",mercado_acoes!G:G,"<=31/12/2023") -> 187
